LICENSE.txt
MANIFEST.in
README.rst
bootstrap.py
buildout.cfg
setup.py
django_sekh.egg-info/PKG-INFO
django_sekh.egg-info/SOURCES.txt
django_sekh.egg-info/dependency_links.txt
django_sekh.egg-info/not-zip-safe
django_sekh.egg-info/requires.txt
django_sekh.egg-info/top_level.txt
sekh/__init__.py
sekh/__init__.pyc
sekh/excerpt.py
sekh/highlighting.py
sekh/middleware.py
sekh/settings.py
sekh/utils.py
sekh/templatetags/__init__.py
sekh/templatetags/sekh_tags.py
sekh/tests/__init__.py
sekh/tests/settings.py
sekh/tests/tests.py