Metadata-Version: 1.1
Name: django-sekh
Version: 0.4
Summary: Highlight the keywords of a page if a visitor is coming form a search engine.
Home-page: https://github.com/Fantomas42/django-sekh
Author: Fantomas42
Author-email: fantomas42@gmail.com
License: BSD License
Keywords: django,search engine,keyword,highlight
Platform: UNKNOWN
Classifier: Framework :: Django
Classifier: Development Status :: 5 - Production/Stable
Classifier: Environment :: Web Environment
Classifier: Programming Language :: Python
Classifier: Programming Language :: Python :: 3
Classifier: Intended Audience :: Developers
Classifier: Operating System :: OS Independent
Classifier: License :: OSI Approved :: BSD License
Classifier: Topic :: Software Development :: Libraries :: Python Modules
